pordego_complexity/__init__.py
pordego_complexity/blocks.py
pordego_complexity/complexity_analysis.py
pordego_complexity/complexity_config.py
pordego_complexity/radon_lib.py
pordego_complexity-1.0.4.dist-info/DESCRIPTION.rst
pordego_complexity-1.0.4.dist-info/METADATA
pordego_complexity-1.0.4.dist-info/RECORD
pordego_complexity-1.0.4.dist-info/WHEEL
pordego_complexity-1.0.4.dist-info/entry_points.txt
pordego_complexity-1.0.4.dist-info/metadata.json
pordego_complexity-1.0.4.dist-info/top_level.txt
