Metadata-Version: 2.0
Name: pordego-complexity
Version: 1.0.4
Summary: Pordego plugin for code complexity analysis using the Radon library
Home-page: https://github.com/ttreptow/pordego-complexity
Author: Tim Treptow
Author-email: tim.treptow@gmail.com
License: The MIT License (MIT)
Requires-Dist: radon (==2.0.0)
